Parser4LLM/__init__.py
Parser4LLM/notification.py
Parser4LLM/parsers.py
Parser4LLM/pdf_converter.py
Parser4LLM/ppt_converter.py
Parser4LLM/url_converter.py
Parser4LLM/word_converter.py
Parser4LLM-0.0.13.dist-info/METADATA
Parser4LLM-0.0.13.dist-info/WHEEL
Parser4LLM-0.0.13.dist-info/top_level.txt
Parser4LLM-0.0.13.dist-info/RECORD
